backlog/__init__.py
backlog/api.py
backlog/models/__init__.py
backlog/models/base.py
backlog/models/const.py
backlog/models/project.py
backlog/models/space.py
backlog/models/user.py
backlog_api4py-0.2.0.dist-info/LICENSE
backlog_api4py-0.2.0.dist-info/METADATA
backlog_api4py-0.2.0.dist-info/WHEEL
backlog_api4py-0.2.0.dist-info/top_level.txt
backlog_api4py-0.2.0.dist-info/RECORD
